{
  "NetworkTables": {
    "Shuffleboard": {
      "Buttons": {
        "open": true
      },
      "open": true
    },
    "SmartDashboard": {
      "open": true
    },
    "types": {
      "/FMSInfo": "FMSInfo",
      "/LiveWindow/Ungrouped/PIDController[1]": "PIDController",
      "/LiveWindow/Ungrouped/PIDController[2]": "PIDController",
      "/SmartDashboard/PID Mode Chooser": "String Chooser",
      "/SmartDashboard/Position PID Controller": "PIDController",
      "/SmartDashboard/Velocity PID Controller": "PIDController"
    },
    "windows": {
      "/SmartDashboard/PID Mode Chooser": {
        "window": {
          "visible": true
        }
      },
      "/SmartDashboard/Position PID Controller": {
        "window": {
          "visible": true
        }
      },
      "/SmartDashboard/Velocity PID Controller": {
        "window": {
          "visible": true
        }
      }
    }
  },
  "NetworkTables Settings": {
    "mode": "Client",
    "serverTeam": "955"
  },
  "Plots": {
    "Plot <0>": {
      "plots": [
        {
          "axis": [
            {
              "autoFit": true
            }
          ],
          "height": 302,
          "series": [
            {
              "color": [
                0.2980392277240753,
                0.44705885648727417,
                0.6901960968971252,
                1.0
              ],
              "id": "NT:/SmartDashboard/Current Velocity"
            }
          ]
        }
      ],
      "window": {
        "name": "Velocity"
      }
    },
    "Plot <1>": {
      "plots": [
        {
          "axis": [
            {
              "autoFit": true
            }
          ],
          "height": 291,
          "series": [
            {
              "color": [
                0.2980392277240753,
                0.44705885648727417,
                0.6901960968971252,
                1.0
              ],
              "id": "NT:/SmartDashboard/Current Position"
            }
          ]
        }
      ],
      "window": {
        "name": "Position"
      }
    }
  }
}
